Metadata-Version: 2.1
Name: pyautoscraper
Version: 0.0.2
Summary: A lightweight python module which automates webscraping and parsing through HTML
Home-page: https://github.com/Jeet-Chugh/pyautoscraper
Author: Jeet Chugh
Author-email: sunjeetchugh@gmail.com
License: MIT
Keywords: pyautoscraper
Platform: UNKNOWN
Classifier: Development Status :: 5 - Production/Stable
Classifier: Intended Audience :: Education
Classifier: Operating System :: Microsoft :: Windows :: Windows 10
Classifier: License :: OSI Approved :: MIT License
Classifier: Programming Language :: Python :: 3
